Metadata-Version: 2.1
Name: funniest-duoduo
Version: 0.2.4
Summary: a ligh weight menu , support both win and mac 
Home-page: https://github.com/wieszheng/Cprint
Author: zhengduoduo
Author-email: 1512945835@qq.com
License: MIT
Keywords: python,menu,dumb_menu,windows,mac,linux
Platform: UNKNOWN
Classifier: Development Status :: 1 - Planning
Classifier: Intended Audience :: Developers
Classifier: Programming Language :: Python :: 3
Classifier: Operating System :: Unix
Classifier: Operating System :: MacOS :: MacOS X
Classifier: Operating System :: Microsoft :: Windows
